hw6/hw6_my/one_digit_sevenseg.vhd
library ieee;
use ieee.std_logic_1164.all;

-- 1 digit 7 segment entity. Do not modify
entity one_digit_sevenseg is
	port(
		in_num: in std_logic_vector(3 downto 0); -- input value (8 digit value / 8 digit value)
		out_num:  out std_logic_vector(6 downto 0) -- 		
	);
end one_digit_sevenseg;

architecture arch_one_digit_sevenseg of one_digit_sevenseg is
	-- Declare your components and signals

begin
   --Define the architecture body
	
	with in_num select
		out_num(6 downto 0) <= "0111111" when "0000",
										"0000110" when "0001",
										"1011011" when "0010",
										"1001111" when "0011",
										"1100110" when "0100",
										"1101101" when "0101",
										"1111101" when "0110",
										"0000111" when "0111",
										"1111111" when "1000",
										"1101111" when "1001",
										"1110111" when "1010",
										"1111100" when "1011",
										"0111001" when "1100",
										"1011110" when "1101",
										"1111001" when "1110",
										"1110001" when "1111",							
										"0000000" when others;
	
	
end arch_one_digit_sevenseg;

hw6/hw6_my/full_adder.vhd
library IEEE;
use IEEE.STD_LOGIC_1164.ALL;

entity full_adder is
	Port( A : in STD_LOGIC;
			B : in STD_LOGIC;
			Cin : in STD_LOGIC;
			S : out STD_LOGIC;
			Cout : out STD_LOGIC);
end full_adder;

architecture arch_full_adder of full_adder is
	begin 
		S <= A XOR B XOR Cin;
		Cout <= (A AND B) OR (Cin AND A) OR (Cin AND B);
end arch_full_adder;

hw6/submission/PE.vhd
library IEEE;
use IEEE.STD_LOGIC_1164.ALL;

entity PE is 
	Port( pin_A : in STD_LOGIC;
			pin_B : in STD_LOGIC;
			pin_1 : in STD_LOGIC;
			pin_2 : in STD_LOGIC;
			
			pout_S : out STD_LOGIC;
			pout_C : out STD_LOGIC);
			
end PE;

architecture arch_PE of PE is
	
	component full_adder
		Port( A : in STD_LOGIC;
				B : in STD_LOGIC;
				Cin : in STD_LOGIC;
				S : out STD_LOGIC;
				Cout : out STD_LOGIC);
	end component;
	
	
	signal pin_0 : STD_LOGIC;
	
	begin 
	
	pin_0 <= pin_A and pin_B;
	
	FA_1 : full_adder port map (pin_0, pin_1, pin_2, pout_S, pout_C);
		
END;

hw6/hw6_my/Row.vhd
library IEEE;
use IEEE.STD_LOGIC_1164.ALL;

entity Row is
	Port( 
			RIn_A : in STD_LOGIC_VECTOR(7 downto 0);
			RIn_B : in STD_LOGIC;	
			RIn_above : in STD_LOGIC_VECTOR(7 downto 0);
			 
			R_Out : out std_logic_vector(8 downto 0)
			);
end Row;



architecture arch_Row of Row is

	component PE
	Port( pin_A : in STD_LOGIC;
			pin_B : in STD_LOGIC;
			pin_1 : in STD_LOGIC;
			pin_2 : in STD_LOGIC;
			
			pout_S : out STD_LOGIC;
			pout_C : out STD_LOGIC);
	end component;
	
	signal internal_C : STD_LOGIC_VECTOR(6 downto 0);
	
	begin 
		
	PE_0 : PE port map (RIn_A(0), RIn_B, RIn_above(0), '0', R_Out(0), internal_C(0));
	PE_1 : PE port map (RIn_A(1), RIn_B, RIn_above(1), internal_C(0), R_Out(1), internal_C(1));
	PE_2 : PE port map (RIn_A(2), RIn_B, RIn_above(2), internal_C(1), R_Out(2), internal_C(2));
	PE_3 : PE port map (RIn_A(3), RIn_B, RIn_above(3), internal_C(2), R_Out(3), internal_C(3));
	PE_4 : PE port map (RIn_A(4), RIn_B, RIn_above(4), internal_C(3), R_Out(4), internal_C(4));	
	PE_5 : PE port map (RIn_A(5), RIn_B, RIn_above(5), internal_C(4), R_Out(5), internal_C(5));
	PE_6 : PE port map (RIn_A(6), RIn_B, RIn_above(6), internal_C(5), R_Out(6), internal_C(6));
	PE_7 : PE port map (RIn_A(7), RIn_B, RIn_above(7), internal_C(6), R_Out(7), R_Out(8));

End;

hw6/submission/mult.vhd
library IEEE;
use IEEE.STD_LOGIC_1164.ALL;

entity mult is
	Port(
			in_num: in std_logic_vector(15 downto 0);
			
			out_num: out std_logic_vector(15 downto 0));
end mult;

architecture arch_mult of mult is
	
	component Row
		Port( 
				RIn_A : in std_logic_vector(7 downto 0);
				RIn_B : in std_logic;	
				RIn_above : in std_logic_vector(7 downto 0);
				 
				R_Out : out std_logic_vector(8 downto 0)
				);
	end component;
	
	signal down_0, down_1 ,down_2,down_3,down_4,down_5,down_6,down_7: std_logic_vector(8 downto 1) ;
	
	begin
	
	Row_0: Row port map (RIn_A(7 downto 0) => in_num(7 downto 0),
								RIn_B => in_num(8),
								RIn_above(7 downto 0) => "00000000",
								R_Out(0) => out_num(0), 
								R_Out(8 downto 1) => down_0(8 downto 1));

	Row_1 : Row port map (RIn_A(7 downto 0) => in_num(7 downto 0),
								 RIn_B => in_num(9),
								RIn_above(6 downto 0)=>down_0(7 downto 1),
								RIn_above(7) =>down_0(8),
								R_Out(0) => out_num(1), 
								R_Out(8 downto 1) => down_1(8 downto 1));

							
	Row_2 : Row port map (RIn_A(7 downto 0) => in_num(7 downto 0),
							 RIn_B => in_num(10),
							RIn_above(6 downto 0)=>down_1(7 downto 1),
							RIn_above(7) =>down_1(8),
							R_Out(0) => out_num(2), 
							R_Out(8 downto 1) => down_2(8 downto 1));
							
	Row_3 : Row port map (RIn_A(7 downto 0) => in_num(7 downto 0),
								 RIn_B => in_num(11),
								RIn_above(6 downto 0)=>down_2(7 downto 1),
								RIn_above(7) =>down_2(8),
								R_Out(0) => out_num(3), 
								R_Out(8 downto 1) => down_3(8 downto 1));
								
	Row_4 : Row port map (RIn_A(7 downto 0) => in_num(7 downto 0),
								 RIn_B => in_num(12),
								RIn_above(6 downto 0)=>down_3(7 downto 1),
								RIn_above(7) =>down_3(8),
								R_Out(0) => out_num(4), 
								R_Out(8 downto 1) => down_4(8 downto 1));
								
	Row_5 : Row port map (RIn_A(7 downto 0) => in_num(7 downto 0),
								 RIn_B => in_num(13),
								RIn_above(6 downto 0)=>down_4(7 downto 1),
								RIn_above(7) =>down_4(8),
								R_Out(0) => out_num(5), 
								R_Out(8 downto 1) => down_5(8 downto 1));
											
	Row_6 : Row port map (RIn_A(7 downto 0) => in_num(7 downto 0),
								 RIn_B => in_num(14),
								RIn_above(6 downto 0)=>down_5(7 downto 1),
								RIn_above(7) =>down_5(8),
								R_Out(0) => out_num(6), 
								R_Out(8 downto 1) => down_6(8 downto 1));
											
						
	Row_7 : Row port map (RIn_A(7 downto 0) => in_num(7 downto 0),
								 RIn_B => in_num(15),
								RIn_above(6 downto 0)=>down_6(7 downto 1),
								RIn_above(7) =>down_6(8),
								R_Out(0) => out_num(7), 
								R_Out(8 downto 1) => out_num(15 downto 8));
											
						
						
							
End arch_mult;

hw6/submission/four_digit_sevenseg.vhd
library ieee;
use ieee.std_logic_1164.all;

-- 4 digit 7 segment entity. Do not modify
entity four_digit_sevenseg is
	port(
		in_num: in std_logic_vector(15 downto 0); -- input value (8 digit value / 8 digit value)
		out_0:  out std_logic_vector(6 downto 0); -- 0th digit (D)
		out_1:  out std_logic_vector(6 downto 0); -- 1th digit (C)
		out_2:  out std_logic_vector(6 downto 0); -- 2nd digit (B)
		out_3:  out std_logic_vector(6 downto 0) -- 3rd digit (A)
	);
end four_digit_sevenseg;

architecture fdss of four_digit_sevenseg is
	-- Declare your components and signals
	component one_digit_sevenseg
		port(
		in_num: in std_logic_vector(3 downto 0); -- input value (8 digit value / 8 digit value)
		out_num:  out std_logic_vector(6 downto 0));
	end component;
	
	component mult
		port(
			in_num: in std_logic_vector(15 downto 0);
			
			out_num: out std_logic_vector(15 downto 0));
	end component;
	
	
	
	signal result_num : std_logic_vector(15 downto 0);

begin
   --Define the architecture body
	
	
	multiply: mult port map (in_num, result_num);
	
	digit_0: one_digit_sevenseg port map (result_num(3 downto 0), out_0(6 downto 0));
	digit_1: one_digit_sevenseg port map (result_num(7 downto 4), out_1(6 downto 0));
	digit_2: one_digit_sevenseg port map (result_num(11 downto 8), out_2(6 downto 0));	
	digit_3: one_digit_sevenseg port map (result_num(15 downto 12), out_3(6 downto 0));	
	
	
	
	
end fdss;

hw6/testbench/tb_four_digit_sevenseg.vhd
library ieee;
use ieee.std_logic_1164.all;
use ieee.numeric_std.all;

entity tb_four_digit_sevenseg is
end tb_four_digit_sevenseg;

architecture tb of tb_four_digit_sevenseg is

	component four_digit_sevenseg is
		port(
			in_num: in std_logic_vector(15 downto 0); -- input value
			out_0:  out std_logic_vector(6 downto 0); -- 0th digit (D)
			out_1:  out std_logic_vector(6 downto 0); -- 1th digit (C)
			out_2:  out std_logic_vector(6 downto 0); -- 2nd digit (B)
			out_3:  out std_logic_vector(6 downto 0) -- 3rd digit (A)
		);
	end component;
	
	signal tb_in_num: std_logic_vector(15 downto 0);
	signal tb_out_0:  std_logic_vector(6 downto 0);
	signal tb_out_1:  std_logic_vector(6 downto 0);
	signal tb_out_2:  std_logic_vector(6 downto 0);
	signal tb_out_3:  std_logic_vector(6 downto 0);
	
begin
	-- unit init
	dut: four_digit_sevenseg port map(
								in_num   => tb_in_num,
								out_0    => tb_out_0,
								out_1    => tb_out_1,
								out_2    =>	tb_out_2,
								out_3    => tb_out_3
								);
	-- process
	process
	begin
		-- 0 0
		tb_in_num <= "0000000000000000";
		wait for 100ns;
		-- 9 135
		tb_in_num <= "0000100110000111";
		wait for 100ns;
		-- 0 97
		tb_in_num <= "0000000001100001";
		wait for 100ns;
		-- 3 2
		tb_in_num <= "0000001100000010";
		wait for 100ns;
		-- 0 5
		tb_in_num <= "0000000000000101";
		wait for 100ns;
		-- 18 52
		tb_in_num <= "0001001000110100";
		wait for 100ns;
		-- 152 118
		tb_in_num <= "1001100001110110";
		wait for 100ns;
		-- 0 5
		tb_in_num <= "0000000000000101";
		wait for 100ns;
		-- 18 52
		tb_in_num <= "0001001000110100";
		wait for 100ns;
		-- 152 118
		tb_in_num <= "1001100001110110";
		wait for 100ns;
	end process;
end tb;

hw6/submission/tb_four_digit_sevenseg.vcd
$date
	Fri Nov 12 18:25:11 2021
$end
$version
	ModelSim Version 2020.1
$end
$timescale
	1ps
$end

$scope module tb_four_digit_sevenseg $end

$scope module dut $end
$var wire 1 ! in_num [15] $end
$var wire 1 " in_num [14] $end
$var wire 1 # in_num [13] $end
$var wire 1 $ in_num [12] $end
$var wire 1 % in_num [11] $end
$var wire 1 & in_num [10] $end
$var wire 1 ' in_num [9] $end
$var wire 1 ( in_num [8] $end
$var wire 1 ) in_num [7] $end
$var wire 1 * in_num [6] $end
$var wire 1 + in_num [5] $end
$var wire 1 , in_num [4] $end
$var wire 1 - in_num [3] $end
$var wire 1 . in_num [2] $end
$var wire 1 / in_num [1] $end
$var wire 1 0 in_num [0] $end
$var wire 1 1 out_0 [6] $end
$var wire 1 2 out_0 [5] $end
$var wire 1 3 out_0 [4] $end
$var wire 1 4 out_0 [3] $end
$var wire 1 5 out_0 [2] $end
$var wire 1 6 out_0 [1] $end
$var wire 1 7 out_0 [0] $end
$var wire 1 8 out_1 [6] $end
$var wire 1 9 out_1 [5] $end
$var wire 1 : out_1 [4] $end
$var wire 1 ; out_1 [3] $end
$var wire 1 < out_1 [2] $end
$var wire 1 = out_1 [1] $end
$var wire 1 > out_1 [0] $end
$var wire 1 ? out_2 [6] $end
$var wire 1 @ out_2 [5] $end
$var wire 1 A out_2 [4] $end
$var wire 1 B out_2 [3] $end
$var wire 1 C out_2 [2] $end
$var wire 1 D out_2 [1] $end
$var wire 1 E out_2 [0] $end
$var wire 1 F out_3 [6] $end
$var wire 1 G out_3 [5] $end
$var wire 1 H out_3 [4] $end
$var wire 1 I out_3 [3] $end
$var wire 1 J out_3 [2] $end
$var wire 1 K out_3 [1] $end
$var wire 1 L out_3 [0] $end
$var wire 1 M result_num [15] $end
$var wire 1 N result_num [14] $end
$var wire 1 O result_num [13] $end
$var wire 1 P result_num [12] $end
$var wire 1 Q result_num [11] $end
$var wire 1 R result_num [10] $end
$var wire 1 S result_num [9] $end
$var wire 1 T result_num [8] $end
$var wire 1 U result_num [7] $end
$var wire 1 V result_num [6] $end
$var wire 1 W result_num [5] $end
$var wire 1 X result_num [4] $end
$var wire 1 Y result_num [3] $end
$var wire 1 Z result_num [2] $end
$var wire 1 [ result_num [1] $end
$var wire 1 \ result_num [0] $end
$upscope $end
$upscope $end
$enddefinitions $end
#0
$dumpvars
01
12
13
14
15
16
17
08
19
1:
1;
1<
1=
1>
0?
1@
1A
1B
1C
1D
1E
0F
1G
1H
1I
1J
1K
1L
0M
0N
0O
0P
0Q
0R
0S
0T
0U
0V
0W
0X
0Y
0Z
0[
0\
0!
0"
0#
0$
0%
0&
0'
0(
0)
0*
0+
0,
0-
0.
0/
00
$end
#100000
10
1/
1.
1)
1(
1%
1Y
1\
1[
1X
03
11
1W
1Z
07
06
13
0>
0;
0:
09
1>
1;
18
17
05
04
1R
0E
0B
0A
1?
1U
0>
0=
1:
19
#200000
0/
0.
1+
1*
0)
0(
0%
0Y
0\
0X
0[
15
14
0Z
0W
1>
1=
0;
07
16
04
03
17
14
13
01
1;
0R
1E
1B
1A
0?
0U
08
#300000
00
1/
0+
0*
1(
1'
1[
1Z
06
11
#400000
10
0/
1.
0(
0'
0Z
0[
16
01
#500000
00
1,
1+
1'
1$
1V
1Y
1S
1T
0>
0;
0:
18
11
1W
0A
0@
1?
0V
1>
0=
1;
1:
1=
0<
09
1U
1<
0;
19
#600000
1/
1*
0'
1%
1!
0T
0S
1Q
1P
1O
1S
1R
0W
1X
1A
1@
0H
0G
1F
1W
0Y
0D
0C
1;
0:
1V
0R
0>
0=
1:
01
0Q
0U
1T
0S
0W
1>
0<
0;
1D
1C
0B
0P
0V
0T
1R
0E
0A
0@
0?
1<
1;
0:
0O
1S
0J
1H
0>
1=
0;
09
08
1@
1?
1N
1J
1G
0F
1E
0D
1B
1A
0L
0I
0H
1F
#700000
10
0/
0,
0+
0*
0%
0$
0!
0S
1O
1P
1Q
1T
0N
0O
0P
1S
1W
0X
0E
1D
0@
1L
0G
0F
0R
1V
0W
1I
1H
1G
1E
0D
0C
0B
1@
1>
0<
1;
1:
18
0V
0T
0S
1R
0E
1C
1B
0>
1<
0;
0:
19
1S
1T
0Q
1>
1;
1:
08
1E
0C
0?
0R
0S
0T
1D
1C
0B
0A
0@
1B
1A
1@
#800000
00
1,
1+
1'
1$
1V
1Y
1S
1T
0>
0;
0:
18
11
1W
0A
0@
1?
0V
1>
0=
1;
1:
1=
0<
09
1U
1<
0;
19
#900000
1/
1*
0'
1%
1!
0T
0S
1Q
1P
1O
1S
1R
0W
1X
1A
1@
0H
0G
1F
1W
0Y
0D
0C
1;
0:
1V
0R
0>
0=
1:
01
0Q
0U
1T
0S
0W
1>
0<
0;
1D
1C
0B
0P
0V
0T
1R
0E
0A
0@
0?
1<
1;
0:
0O
1S
0J
1H
0>
1=
0;
09
08
1@
1?
1N
1J
1G
0F
1E
0D
1B
1A
0L
0I
0H
1F
#1000000
0/
0.
0,
0+
0*
0%
0$
0!
1O
1P
1Q
0S
1T
0N
0O
0P
1S
1W
0X
1L
0G
0F
0E
1D
0@
0R
0W
1V
1I
1H
1G
1E
0D
0C
0B
1@
1>
0<
1;
1:
18
0V
0T
0S
1R
0E
1C
1B
0>
1<
0;
0:
19
1S
1T
0Q
1>
1;
1:
08
1E
0C
0?
0R
0S
0T
1D
1C
0B
0A
0@
1B
1A
1@
